suit_redactor/__init__.py
suit_redactor/models.py
suit_redactor/widgets.py
suit_redactor/static/suit-redactor/redactor/ensure.jquery.js
suit_redactor/static/suit-redactor/redactor/redactor.css
suit_redactor/static/suit-redactor/redactor/redactor.js
suit_redactor/static/suit-redactor/redactor/redactor.min.js
suit_redactor/static/suit-redactor/redactor/style.css
django_suit_redactor_django2-0.5.3.dist-info/METADATA
django_suit_redactor_django2-0.5.3.dist-info/WHEEL
django_suit_redactor_django2-0.5.3.dist-info/top_level.txt
django_suit_redactor_django2-0.5.3.dist-info/RECORD
