Metadata-Version: 2.1
Name: django-suit-redactor-django2
Version: 0.5.3
Summary: Imperavi Redactor (WYSIWYG editor) integration app for Django admin. http://imperavi.com/redactor/
Home-page: https://github.com/avryhof/django-suit-redactor
Author: Kaspars Sprogis (darklow) enhanced by Amos Vryhof (avryhof)
Author-email: info@djangosuit.com
Classifier: Development Status :: 5 - Production/Stable
Classifier: Framework :: Django
Classifier: License :: Free for non-commercial use
Classifier: Intended Audience :: Developers
Classifier: Intended Audience :: System Administrators
Classifier: Programming Language :: Python
Classifier: Environment :: Web Environment
Classifier: Topic :: Software Development :: User Interfaces
Requires-Dist: django (<4.0,>2.1)
Requires-Dist: django-suit
